{
    "2025-07-15 00:00:00": [
        {
            "user": "U0915RNR70S",
            "type": "message",
            "ts": "1752587899.914049",
            "client_msg_id": "01e16ac5-95fd-45e7-8b4e-19179d4a87c2",
            "text": "July 14-15\n1) Work on the Tofu for the digital ocean infra. And tested the infra with the <@U07UB6TQWRE>",
            "team": "TC99SV7B6",
            "blocks": [
                {
                    "type": "rich_text",
                    "block_id": "PSLOC",
                    "elements": [
                        {
                            "type": "rich_text_section",
                            "elements": [
                                {
                                    "type": "text",
                                    "text": "July 14-15\n1) Work on the Tofu for the digital ocean infra. And tested the infra with the "
                                },
                                {
                                    "type": "user",
                                    "user_id": "U07UB6TQWRE"
                                }
                            ]
                        }
                    ]
                }
            ]
        }
    ]
}